examples/rec_DL.py
examples/rec_Hz.py
examples/rec_xsin.py
examples/data/Hz31.txt
examples/data/Union2.1_DL.txt
refann/__init__.py
refann/data_process.py
refann/element.py
refann/evaluate.py
refann/fcnet.py
refann/hpmodel.py
refann/nodeframe.py
refann/optimize.py
refann/refann.py
refann/save.py
refann/sequence.py
refann/train.py
refann-1.0.2.data/data/Hz31.txt
refann-1.0.2.data/data/Union2.1_DL.txt
refann-1.0.2.dist-info/METADATA
refann-1.0.2.dist-info/WHEEL
refann-1.0.2.dist-info/top_level.txt
refann-1.0.2.dist-info/RECORD
