Metadata-Version: 2.1
Name: refann
Version: 1.0.2
Summary: Reconstruct Functions with Artificial Neural Network
Home-page: UNKNOWN
Author: Guojian Wang
Author-email: gjwang@mail.bnu.edu.cn
License: MIT
Keywords: pip,ANN
Platform: any
